clawd_code_sdk/__init__.py
clawd_code_sdk/_cli_version.py
clawd_code_sdk/_errors.py
clawd_code_sdk/_version.py
clawd_code_sdk/anthropic_types.py
clawd_code_sdk/client.py
clawd_code_sdk/py.typed
clawd_code_sdk/query.py
clawd_code_sdk/types.py
clawd_code_sdk/_bundled/.gitignore
clawd_code_sdk/_internal/__init__.py
clawd_code_sdk/_internal/client.py
clawd_code_sdk/_internal/message_parser.py
clawd_code_sdk/_internal/query.py
clawd_code_sdk/_internal/transport/__init__.py
clawd_code_sdk/_internal/transport/subprocess_cli.py
clawd_code_sdk-0.1.36.dist-info/METADATA
clawd_code_sdk-0.1.36.dist-info/WHEEL
clawd_code_sdk-0.1.36.dist-info/licenses/LICENSE
clawd_code_sdk-0.1.36.dist-info/RECORD
