Metadata-Version: 2.4
Name: clawd-code-sdk
Version: 0.1.36
Summary: Python SDK for Claude Code
Project-URL: Documentation, https://github.com/phil65/claude-agent-sdk-python
Project-URL: Homepage, https://github.com/phil65/claude-agent-sdk-python
Project-URL: Issues, https://github.com/phil65/claude-agent-sdk-python/issues
Author-email: phil65 <philipptemminghoff@gmail.com>
License: MIT
License-File: LICENSE
Keywords: ai,anthropic,claude,sdk
Classifier: Development Status :: 3 - Alpha
Classifier: Intended Audience :: Developers
Classifier: License :: OSI Approved :: MIT License
Classifier: Programming Language :: Python :: 3
Classifier: Programming Language :: Python :: 3.13
Classifier: Programming Language :: Python :: 3.14
Classifier: Typing :: Typed
Requires-Python: >=3.13
Requires-Dist: anthropic>=0.77.0
Requires-Dist: anyenv>=2.0.15
Requires-Dist: anyio>=4.0.0
Requires-Dist: mcp>=0.1.0
Provides-Extra: dev
Requires-Dist: anyio[trio]>=4.0.0; extra == 'dev'
Requires-Dist: mypy>=1.0.0; extra == 'dev'
Requires-Dist: pytest-asyncio>=0.20.0; extra == 'dev'
Requires-Dist: pytest-cov>=4.0.0; extra == 'dev'
Requires-Dist: pytest-timeout>=2.4.0; extra == 'dev'
Requires-Dist: pytest>=7.0.0; extra == 'dev'
Requires-Dist: ruff>=0.1.0; extra == 'dev'
